printb/__init__.py
printb/print_help.py
printb-1.0.2.dist-info/LICENSE.txt
printb-1.0.2.dist-info/METADATA
printb-1.0.2.dist-info/WHEEL
printb-1.0.2.dist-info/top_level.txt
printb-1.0.2.dist-info/RECORD
