Metadata-Version: 2.1
Name: printb
Version: 1.0.2
Summary: printb is a wrapper for print/input built-ins, that swaps string directions for BIDI languages.
Home-page: https://github.com/MoserMichael/printb
Author: Michael Moser
Author-email: moser.michael@gmail.com
License: MIT
Keywords: text processing,bidi languages
Platform: UNKNOWN
Classifier: Programming Language :: Python :: 3
Classifier: License :: OSI Approved :: MIT License
Classifier: Operating System :: OS Independent
Classifier: Topic :: Text Processing
Requires-Python: >=3.6
Requires-Dist: python-bidi (==0.4.2)
Requires-Dist: six (==1.16.0)
